pupilanalysis/__init__.py
pupilanalysis/antenna_level.py
pupilanalysis/binary_search.py
pupilanalysis/coordinates.py
pupilanalysis/directories.py
pupilanalysis/droso.py
pupilanalysis/image_tools.py
pupilanalysis/rotary_encoders.py
pupilanalysis/settings.py
pupilanalysis/version.py
pupilanalysis/drosom/__init__.py
pupilanalysis/drosom/analyser_commands.py
pupilanalysis/drosom/analysing.py
pupilanalysis/drosom/fitting.py
pupilanalysis/drosom/kinematics.py
pupilanalysis/drosom/loading.py
pupilanalysis/drosom/optic_flow.py
pupilanalysis/drosom/orientation_analysis.py
pupilanalysis/drosom/sinesweep.py
pupilanalysis/drosom/terminal.py
pupilanalysis/drosom/linked_data/__init__.py
pupilanalysis/drosom/linked_data/electrophysiology.py
pupilanalysis/drosom/plotting/__init__.py
pupilanalysis/drosom/plotting/basics.py
pupilanalysis/drosom/plotting/common.py
pupilanalysis/drosom/plotting/compare_opticflow.py
pupilanalysis/drosom/plotting/illustrate_experiments.py
pupilanalysis/drosom/plotting/plotter.py
pupilanalysis/drosom/reports/__init__.py
pupilanalysis/drosom/reports/left_right.py
pupilanalysis/drosom/reports/pdf_summary.py
pupilanalysis/drosom/reports/stats.py
pupilanalysis/drosom/special/__init__.py
pupilanalysis/drosom/special/norpa_rescues.py
pupilanalysis/drosom/special/paired.py
pupilanalysis/tkgui/__init__.py
pupilanalysis/tkgui/__main__.py
pupilanalysis/tkgui/core.py
pupilanalysis/tkgui/examine.py
pupilanalysis/tkgui/menu_commands.py
pupilanalysis/tkgui/plotting.py
pupilanalysis/tkgui/repetition_selection.py
pupilanalysis/tkgui/run_measurement.py
pupilanalysis/tkgui/settings.py
pupilanalysis/tkgui/waiting_window.py
pupilanalysis/tkgui/zero_correct.py
pupil_analysis-0.4.1.dist-info/LICENSE
pupil_analysis-0.4.1.dist-info/METADATA
pupil_analysis-0.4.1.dist-info/WHEEL
pupil_analysis-0.4.1.dist-info/top_level.txt
pupil_analysis-0.4.1.dist-info/RECORD
