Metadata-Version: 2.1
Name: pupil-analysis
Version: 0.4.1
Summary: Spatial motion analysis program
Home-page: https://github.com/jkemppainen/pupil-analysis
Author: Joni Kemppainen
Author-email: jjtkemppainen1@sheffield.ac.uk
License: UNKNOWN
Platform: UNKNOWN
Classifier: Programming Language :: Python :: 3
Classifier: License :: OSI Approved :: GNU General Public License v3 (GPLv3) 
Classifier: Operating System :: OS Independent
Requires-Python: >=3.0
Requires-Dist: numpy
Requires-Dist: scipy
Requires-Dist: tifffile
Requires-Dist: matplotlib
Requires-Dist: tk-steroids (>=0.6.0)
Requires-Dist: roimarker (>=0.2.0)
Requires-Dist: movemeter (>=0.4.0)
Requires-Dist: python-biosystfiles
